[
	{
		"url": "https://www.susanpotter.net/software/work-from-home-work-and-home-separation-tips/",
		"name": "Work-from-Home Work and Home Separation Tips",
		"author": "Susan Potter",
		"readOn": "Unknown"
	},
	{
		"url": "https://news.ncsu.edu/2020/07/tech-job-interviews-anxiety/",
		"name": "Tech Sector Job Interviews Assess Anxiety, Not Software Skills",
		"author": "Mahnaz Behroozi, Shivani Shirolkar, Chris Parnin, and Titus Barik",
		"readOn": "Unknown"
	},
	{
		"url": "https://blog.danslimmon.com/2023/08/11/squeeze-the-hell-out-of-the-system-you-have/",
		"name": "Squeeze the hell out of the system you have",
		"author": "Dan Slimmon",
		"readOn": "Unknown"
	},
	{
		"url": "https://www.bitecode.dev/p/hype-cycles",
		"name": "XML is the future",
		"author": "Bite Code",
		"readOn": "Unknown"
	},
	{
		"url": "https://tonsky.me/blog/unicode/",
		"name": "The Absolute Minimum Every Software Developer Must Know About Unicode in 2023 (Still No Excuses!)",
		"author": "Niki",
		"readOn": "2023-12-13T00:00:00"
	},
	{
		"url": "https://www.rollingstone.com/culture/culture-commentary/internet-future-about-to-get-weird-1234938403/",
		"name": "The Internet Is About to Get Weird Again",
		"author": "Anil Dash",
		"readOn": "2024-01-10T00:00:00"
	},
	{
		"url": "https://geoffgraham.me/hey-will-you-build-me-a-website/",
		"name": "Hey, will you build me a website?",
		"author": "Geoff Graham",
		"readOn": "2024-02-17T00:00:00"
	},
	{
		"url": "https://ericwbailey.website/published/thoughts-on-embedding-alternative-text-metadata-into-images/",
		"name": "Thoughts on embedding alternative text metadata into images",
		"author": "Eric Bailey",
		"readOn": "2024-03-16T00:00:00"
	},
	{
		"url": "https://www.takahe.org.nz/heat-death-of-the-internet/",
		"name": "Heat Death of the Internet",
		"author": "Gregory Bennett",
		"readOn": "2024-04-05T00:00:00"
	},
	{
		"url": "https://cruncher.ch/blog/printing-music-with-css-grid/",
		"name": "Printing music with CSS Grid",
		"author": "Stephen Band",
		"readOn": "2024-04-26T00:00:00"
	},
    {
        "url": "https://pcalv.es/offboarding/",
        "name": "Offboarding",
		"author": "pcalves",
		"readOn": "2024-07-04T00:00:00"
    },
	{
		"url": "https://daught.me/blog/2024/indie-web/",
		"name": "The \"IndieWeb\" feels like coming home",
		"author": "Nathaniel Daught",
		"readOn": "2024-07-09T00:00:00"
	},
	{
		"url": "https://birchtree.me/blog/the-public-web-and-consent/",
		"name": "The public web and consent",
		"author": "Matt Birchler",
		"readOn": "2024-07-09T00:00:00"
	},
	{
		"url": "https://chriscoyier.net/2024/07/13/its-really-this-thing-that-gets-me/",
		"name": "It's really this thing that gets me.",
		"author": "Chris Coyier",
		"readOn": "2024-07-14T00:00:00"
	},
	{
		"url": "https://wouterj.nl/2024/08/git-notes",
		"name": "Store Code Discussions in Git using Git Notes",
		"author": "Wouter de Jong",
		"readOn": "2024-08-08T00:00:00"
	},
 {
		"url": "https://kerkour.com/sqlite-for-servers",
		"name": "Optimizing SQLite for servers",
		"author": "Sylvain Kerkour",
		"readOn": "2024-09-28T00:00:00"
	}
]